sphinxcontrib/external_links/__init__.py
sphinxcontrib/external_links/_case_insensitive_mapping.py
sphinxcontrib/external_links/_roles.py
sphinxcontrib/external_links/_transforms.py
sphinxcontrib/external_links/constants.py
sphinxcontrib/external_links/py.typed
sphinxcontrib/external_links/type_defs.py
sphinxcontrib_external_links-0.1.1.dist-info/LICENSE
sphinxcontrib_external_links-0.1.1.dist-info/METADATA
sphinxcontrib_external_links-0.1.1.dist-info/WHEEL
sphinxcontrib_external_links-0.1.1.dist-info/RECORD
