Metadata-Version: 2.1
Name: sphinxcontrib.external-links
Version: 0.1.1
Summary: Sphinx extension for easily adding reusable external links.
Home-page: https://github.com/ITProKyle/sphinxcontrib.external-links
License: Apache-2.0
Keywords: documentation,extension,sphinx
Author: Kyle Finley
Author-email: kyle@finley.sh
Requires-Python: >=3.9,<4.0
Classifier: Framework :: Sphinx :: Extension
Classifier: Intended Audience :: Developers
Classifier: License :: OSI Approved :: Apache Software License
Classifier: Natural Language :: English
Classifier: Operating System :: OS Independent
Classifier: Programming Language :: Python :: 3
Classifier: Programming Language :: Python :: 3.9
Classifier: Programming Language :: Python :: 3.10
Classifier: Programming Language :: Python :: 3.11
Classifier: Programming Language :: Python :: 3.12
Classifier: Topic :: Documentation :: Sphinx
Classifier: Topic :: Software Development :: Documentation
Requires-Dist: sphinx (>=7.2,<9)
Project-URL: Documentation, https://sphinxcontribexternal-links.readthedocs.io/
Project-URL: Repository, https://github.com/ITProKyle/sphinxcontrib.external-links
Project-URL: bugs, https://github.com/ITProKyle/sphinxcontrib.external-links/issues
Project-URL: changelog, https://github.com/ITProKyle/sphinxcontrib.external-links/releases
Project-URL: issues, https://github.com/ITProKyle/sphinxcontrib.external-links/issues
